db_delta/__init__.py
db_delta/models.py
db_delta/validate.py
db_delta-1.0.3.dist-info/licenses/LICENSE
db_delta-1.0.3.dist-info/METADATA
db_delta-1.0.3.dist-info/WHEEL
db_delta-1.0.3.dist-info/top_level.txt
db_delta-1.0.3.dist-info/RECORD
