Metadata-Version: 2.4
Name: db_delta
Version: 1.0.3
Summary: Python library to evaluate DynamoDB changesets when running database unittests.
Author-email: Pascal Sauerborn <pascal.sauerborn@gmail.com>
Project-URL: Repository, https://github.com/alpinesoftwareltd/db-delta.git
Project-URL: Homepage, https://github.com/alpinesoftwareltd/db-delta
Project-URL: Documentation, https://github.com/alpinesoftwareltd/db-delta/blob/main/README.md
License-File: LICENSE
Requires-Dist: pydantic
Requires-Dist: moto
Requires-Dist: boto3
Dynamic: license-file
